oreum_core/__init__.py
oreum_core/curate/.gitkeep
oreum_core/curate/__init__.py
oreum_core/curate/data_io.py
oreum_core/curate/data_transform.py
oreum_core/curate/text_clean.py
oreum_core/eda/.gitkeep
oreum_core/eda/__init__.py
oreum_core/eda/calc.py
oreum_core/eda/describe.py
oreum_core/eda/eda_io.py
oreum_core/eda/plot.py
oreum_core/model_pymc/.gitkeep
oreum_core/model_pymc/__init__.py
oreum_core/model_pymc/base.py
oreum_core/model_pymc/calc.py
oreum_core/model_pymc/describe.py
oreum_core/model_pymc/distributions.py
oreum_core/model_pymc/plot.py
oreum_core/model_pymc/pymc_io.py
oreum_core/model_tree/.gitkeep
oreum_core/model_tree/__init__.py
oreum_core/model_tree/tree_io.py
oreum_core/utils/.gitkeep
oreum_core/utils/__init__.py
oreum_core/utils/file_io.py
oreum_core/utils/snakey_lowercaser.py
oreum_core-0.11.5.dist-info/licenses/LICENSE.md
oreum_core-0.11.5.dist-info/licenses/LICENSES_3P.md
oreum_core-0.11.5.dist-info/WHEEL
oreum_core-0.11.5.dist-info/METADATA
oreum_core-0.11.5.dist-info/RECORD
