Metadata-Version: 2.4
Name: oreum_core
Version: 0.11.5
Summary: Core tools for use on projects by Oreum Industries
Author-email: Oreum Industries <info@oreum.io>
Requires-Python: ==3.13.*
Classifier: Development Status :: 4 - Beta
Classifier: Intended Audience :: Science/Research
Classifier: Intended Audience :: Financial and Insurance Industry
Classifier: License :: OSI Approved :: Apache Software License
Classifier: Natural Language :: English
Classifier: Operating System :: MacOS
Classifier: Operating System :: Unix
Classifier: Programming Language :: Python
Classifier: Programming Language :: Python :: 3
Classifier: Programming Language :: Python :: 3.13
Classifier: Topic :: Scientific/Engineering
Classifier: Topic :: Scientific/Engineering :: Information Analysis
Classifier: Topic :: Scientific/Engineering :: Visualization
License-File: LICENSE.md
License-File: LICENSES_3P.md
Requires-Dist: csv2md
Requires-Dist: dask
Requires-Dist: fastparquet
Requires-Dist: ftfy
Requires-Dist: matplotlib
Requires-Dist: matplotlib-inline
Requires-Dist: pandas[excel, parquet, plot]==2.3.*
Requires-Dist: patsy
Requires-Dist: scikit-learn
Requires-Dist: scipy
Requires-Dist: seaborn<0.14
Requires-Dist: statsmodels
Requires-Dist: umap-learn
Requires-Dist: bandit ; extra == "dev"
Requires-Dist: hypothesis ; extra == "dev"
Requires-Dist: interrogate ; extra == "dev"
Requires-Dist: ipython ; extra == "dev"
Requires-Dist: meson ; extra == "dev"
Requires-Dist: ninja ; extra == "dev"
Requires-Dist: pipdeptree ; extra == "dev"
Requires-Dist: pip-licenses ; extra == "dev"
Requires-Dist: pooch ; extra == "dev"
Requires-Dist: pre-commit ; extra == "dev"
Requires-Dist: pytest ; extra == "dev"
Requires-Dist: ruff ; extra == "dev"
Requires-Dist: graphviz ; extra == "pymc"
Requires-Dist: pymc ; extra == "pymc"
Requires-Dist: catboost ; extra == "tree"
Requires-Dist: category_encoders ; extra == "tree"
Requires-Dist: graphviz ; extra == "tree"
Requires-Dist: optuna ; extra == "tree"
Requires-Dist: optuna-integration ; extra == "tree"
Requires-Dist: nbformat ; extra == "tree"
Requires-Dist: shap ; extra == "tree"
Requires-Dist: xgboost ; extra == "tree"
Project-URL: Homepage, https://github.com/oreum-industries/oreum_core
Provides-Extra: dev
Provides-Extra: pymc
Provides-Extra: tree
